setup.py
muse/__init__.py
muse/bugs.py
muse/genie.py
muse/melon.py
muse/util.py
music_chart_api.egg-info/PKG-INFO
music_chart_api.egg-info/SOURCES.txt
music_chart_api.egg-info/dependency_links.txt
music_chart_api.egg-info/requires.txt
music_chart_api.egg-info/top_level.txt