Metadata-Version: 1.0
Name: music-chart-api
Version: 0.1.1
Summary: Korean music chart API
Home-page: https://github.com/DSMdongly/Muse
Author: Toygrammer
Author-email: gdh0608@naver.com
License: MIT
Platform: UNKNOWN
